hey_mcp_test/__init__.py
hey_mcp_test/__main__.py
hey_mcp_test/server.py
hey_mcp_test-1.4.1.dist-info/METADATA
hey_mcp_test-1.4.1.dist-info/WHEEL
hey_mcp_test-1.4.1.dist-info/entry_points.txt
hey_mcp_test-1.4.1.dist-info/RECORD
